osm_helper/__init__.py
osm_helper/config.py
osm_helper/docs/img/osrm_python.png
osm_helper/examples/__init__.py
osm_helper/examples/advanced.py
osm_helper/examples/basic.py
osm_helper/examples/simple.py
osm_helper/locations.py
osm_helper/osm_api.py
osm_helper/tests/__init__.py
osm_helper/tests/test_config.py
osm_helper/tests/test_locations.py
osm_helper/tests/test_osm_api.py
osm_helper/tests/test_utils.py
osm_helper/utils/__init__.py
osm_helper/utils/redis.py
osm_helper/utils/type_hints.py
osm_helper-0.0.8.dist-info/LICENSE
osm_helper-0.0.8.dist-info/METADATA
osm_helper-0.0.8.dist-info/WHEEL
osm_helper-0.0.8.dist-info/RECORD
