Metadata-Version: 2.1
Name: osm_helper
Version: 0.0.8
Summary: A fast way to get the ETA for the logistics projects that depends heavily on it
License: MIT
Author: Waseem Kntar
Author-email: waseem.kntar@gmail.com
Requires-Python: >=3.8
Classifier: License :: OSI Approved :: MIT License
Classifier: Programming Language :: Python :: 3
Classifier: Programming Language :: Python :: 3.8
Classifier: Programming Language :: Python :: 3.9
Classifier: Programming Language :: Python :: 3.10
Classifier: Programming Language :: Python :: 3.11
Classifier: Programming Language :: Python :: 3.12
Classifier: Programming Language :: Python :: 3.13
Requires-Dist: python-dotenv (>=1.0.0)
Requires-Dist: pyyaml (>=6.0.1,<7.0.0)
Requires-Dist: redis (>=4.6.0)
Requires-Dist: requests (>=2.31.0)
Project-URL: Bug Tracker, https://github.com/mo-waseem/osm-helper/issues
Project-URL: Homepage, https://github.com/mo-waseem/osm-helper
